NALU-0.0.4.dist-info/METADATA
NALU-0.0.4.dist-info/RECORD
NALU-0.0.4.dist-info/WHEEL
NALU-0.0.4.dist-info/top_level.txt
nalu/__init__.py
nalu/core/__init__.py
nalu/core/nac_cell.py
nalu/core/nalu_cell.py
nalu/layers/__init__.py
nalu/layers/nalu_layer.py
tests/__init__.py
