Metadata-Version: 2.1
Name: NALU
Version: 0.0.4
Summary: basic implementation of Neural arithmetic and logic units as described in arxiv.org/pdf/1808.00508.pdf
Home-page: https://github.com/bharathgs/NALU
Author: Bharath G.S
Author-email: royalkingpin@gmail.com
Maintainer: Bharath G.S
Maintainer-email: royalkingpin@gmail.com
License: MIT
Keywords: NALU,ALU,neural,neural-networks,pytorch,NAC,torch,machine-learning
Platform: UNKNOWN
Classifier: Development Status :: 4 - Beta
Classifier: Intended Audience :: Developers
Classifier: License :: OSI Approved :: MIT License
Classifier: Natural Language :: English
Classifier: Operating System :: OS Independent
Classifier: Programming Language :: Python :: 3.6
Classifier: Programming Language :: Python :: Implementation :: CPython
Requires-Dist: torch
Requires-Dist: numpy
